PythonXuexiYuan/README.md
PythonXuexiYuan/__init__.py
PythonXuexiYuan/__main__.py
PythonXuexiYuan/file.epub
PythonXuexiYuan/index.html
PythonXuexiYuan/css/__init__.py
PythonXuexiYuan/css/annotations.css
PythonXuexiYuan/css/main.css
PythonXuexiYuan/css/normalize.css
PythonXuexiYuan/css/popup.css
PythonXuexiYuan/font/__init__.py
PythonXuexiYuan/font/fontello.eot
PythonXuexiYuan/font/fontello.svg
PythonXuexiYuan/font/fontello.ttf
PythonXuexiYuan/font/fontello.woff
PythonXuexiYuan/img/__init__.py
PythonXuexiYuan/img/annotator-glyph-sprite.png
PythonXuexiYuan/img/annotator-icon-sprite.png
PythonXuexiYuan/img/apple-touch-icon.png
PythonXuexiYuan/img/cancelfullscreen.png
PythonXuexiYuan/img/close.png
PythonXuexiYuan/img/fullscreen.png
PythonXuexiYuan/img/loader.gif
PythonXuexiYuan/img/menu-icon.png
PythonXuexiYuan/img/save.png
PythonXuexiYuan/img/saved.png
PythonXuexiYuan/img/settings-s.png
PythonXuexiYuan/img/settings.png
PythonXuexiYuan/img/star.png
PythonXuexiYuan/js/__init__.py
PythonXuexiYuan/js/epub.js
PythonXuexiYuan/js/epub.min.js
PythonXuexiYuan/js/epub.min.map
PythonXuexiYuan/js/hooks.min.js
PythonXuexiYuan/js/hooks.min.map
PythonXuexiYuan/js/reader.js
PythonXuexiYuan/js/reader.js.map
PythonXuexiYuan/js/reader.min.js
PythonXuexiYuan/js/reader.min.map
PythonXuexiYuan/js/hooks/__init__.py
PythonXuexiYuan/js/hooks/extensions/__init__.py
PythonXuexiYuan/js/hooks/extensions/highlight.js
PythonXuexiYuan/js/libs/__init__.py
PythonXuexiYuan/js/libs/jquery.min.js
PythonXuexiYuan/js/libs/localforage.min.js
PythonXuexiYuan/js/libs/screenfull.js
PythonXuexiYuan/js/libs/screenfull.min.js
PythonXuexiYuan/js/libs/zip.min.js
PythonXuexiYuan/js/plugins/__init__.py
PythonXuexiYuan/js/plugins/hypothesis.js
PythonXuexiYuan/js/plugins/search.js
python_xuexi_yuan-2024.3.5.0.dist-info/METADATA
python_xuexi_yuan-2024.3.5.0.dist-info/WHEEL
python_xuexi_yuan-2024.3.5.0.dist-info/entry_points.txt
python_xuexi_yuan-2024.3.5.0.dist-info/top_level.txt
python_xuexi_yuan-2024.3.5.0.dist-info/RECORD
